amber_actuator-0.0.4.dist-info/METADATA
amber_actuator-0.0.4.dist-info/WHEEL
amber_actuator-0.0.4.dist-info/licenses/LICENSE
amber_actuator/.ropeproject/history
amber_actuator/.ropeproject/history.json
amber_actuator/Amber_actuator.py
amber_actuator/__init__.py
amber_actuator/setPos.py
amber_actuator-0.0.4.dist-info/RECORD
