Metadata-Version: 2.1
Name: amber_actuator
Version: 0.0.4
Summary: Python Interface for Amber Actuator
Author-Email: Amberobotics <songtianren@amberobotics.com>
License: MIT
Requires-Python: >=3.10
